{
  "version": "8",
  "dialect": "postgres",
  "id": "9ef06127-034f-446b-91cc-ffa94fde040d",
  "prevIds": [
    "00000000-0000-0000-0000-000000000000"
  ],
  "ddl": [
    {
      "isRlsEnabled": false,
      "name": "contents",
      "entityType": "tables",
      "schema": "public"
    },
    {
      "isRlsEnabled": false,
      "name": "links",
      "entityType": "tables",
      "schema": "public"
    },
    {
      "isRlsEnabled": false,
      "name": "metadata",
      "entityType": "tables",
      "schema": "public"
    },
    {
      "isRlsEnabled": false,
      "name": "search_index",
      "entityType": "tables",
      "schema": "public"
    },
    {
      "isRlsEnabled": false,
      "name": "urls",
      "entityType": "tables",
      "schema": "public"
    },
    {
      "type": "integer",
      "typeSchema": null,
      "notNull": true,
      "dimensions": 0,
      "default": null,
      "generated": null,
      "identity": {
        "type": "always",
        "name": "contents_id_seq",
        "increment": "1",
        "startWith": "1",
        "minValue": "1",
        "maxValue": "2147483647",
        "cache": 1,
        "cycle": false
      },
      "name": "id",
      "entityType": "columns",
      "schema": "public",
      "table": "contents"
    },
    {
      "type": "integer",
      "typeSchema": null,
      "notNull": true,
      "dimensions": 0,
      "default": null,
      "generated": null,
      "identity": null,
      "name": "url_id",
      "entityType": "columns",
      "schema": "public",
      "table": "contents"
    },
    {
      "type": "varchar(255)",
      "typeSchema": null,
      "notNull": false,
      "dimensions": 0,
      "default": null,
      "generated": null,
      "identity": null,
      "name": "title",
      "entityType": "columns",
      "schema": "public",
      "table": "contents"
    },
    {
      "type": "text",
      "typeSchema": null,
      "notNull": false,
      "dimensions": 0,
      "default": null,
      "generated": null,
      "identity": null,
      "name": "text_content",
      "entityType": "columns",
      "schema": "public",
      "table": "contents"
    },
    {
      "type": "text",
      "typeSchema": null,
      "notNull": false,
      "dimensions": 0,
      "default": null,
      "generated": null,
      "identity": null,
      "name": "metadata",
      "entityType": "columns",
      "schema": "public",
      "table": "contents"
    },
    {
      "type": "text",
      "typeSchema": null,
      "notNull": false,
      "dimensions": 0,
      "default": null,
      "generated": null,
      "identity": null,
      "name": "html_source",
      "entityType": "columns",
      "schema": "public",
      "table": "contents"
    },
    {
      "type": "timestamp with time zone",
      "typeSchema": null,
      "notNull": false,
      "dimensions": 0,
      "default": "now()",
      "generated": null,
      "identity": null,
      "name": "created_at",
      "entityType": "columns",
      "schema": "public",
      "table": "contents"
    },
    {
      "type": "integer",
      "typeSchema": null,
      "notNull": true,
      "dimensions": 0,
      "default": null,
      "generated": null,
      "identity": {
        "type": "always",
        "name": "links_id_seq",
        "increment": "1",
        "startWith": "1",
        "minValue": "1",
        "maxValue": "2147483647",
        "cache": 1,
        "cycle": false
      },
      "name": "id",
      "entityType": "columns",
      "schema": "public",
      "table": "links"
    },
    {
      "type": "integer",
      "typeSchema": null,
      "notNull": false,
      "dimensions": 0,
      "default": null,
      "generated": null,
      "identity": null,
      "name": "source_url_id",
      "entityType": "columns",
      "schema": "public",
      "table": "links"
    },
    {
      "type": "varchar(255)",
      "typeSchema": null,
      "notNull": false,
      "dimensions": 0,
      "default": null,
      "generated": null,
      "identity": null,
      "name": "source_url",
      "entityType": "columns",
      "schema": "public",
      "table": "links"
    },
    {
      "type": "varchar(255)",
      "typeSchema": null,
      "notNull": true,
      "dimensions": 0,
      "default": null,
      "generated": null,
      "identity": null,
      "name": "target_url",
      "entityType": "columns",
      "schema": "public",
      "table": "links"
    },
    {
      "type": "text",
      "typeSchema": null,
      "notNull": false,
      "dimensions": 0,
      "default": null,
      "generated": null,
      "identity": null,
      "name": "anchor_text",
      "entityType": "columns",
      "schema": "public",
      "table": "links"
    },
    {
      "type": "varchar(20)",
      "typeSchema": null,
      "notNull": false,
      "dimensions": 0,
      "default": "'internal'",
      "generated": null,
      "identity": null,
      "name": "link_type",
      "entityType": "columns",
      "schema": "public",
      "table": "links"
    },
    {
      "type": "timestamp with time zone",
      "typeSchema": null,
      "notNull": false,
      "dimensions": 0,
      "default": "now()",
      "generated": null,
      "identity": null,
      "name": "created_at",
      "entityType": "columns",
      "schema": "public",
      "table": "links"
    },
    {
      "type": "integer",
      "typeSchema": null,
      "notNull": true,
      "dimensions": 0,
      "default": null,
      "generated": null,
      "identity": {
        "type": "always",
        "name": "metadata_id_seq",
        "increment": "1",
        "startWith": "1",
        "minValue": "1",
        "maxValue": "2147483647",
        "cache": 1,
        "cycle": false
      },
      "name": "id",
      "entityType": "columns",
      "schema": "public",
      "table": "metadata"
    },
    {
      "type": "integer",
      "typeSchema": null,
      "notNull": true,
      "dimensions": 0,
      "default": null,
      "generated": null,
      "identity": null,
      "name": "url_id",
      "entityType": "columns",
      "schema": "public",
      "table": "metadata"
    },
    {
      "type": "varchar(100)",
      "typeSchema": null,
      "notNull": false,
      "dimensions": 0,
      "default": null,
      "generated": null,
      "identity": null,
      "name": "content_type",
      "entityType": "columns",
      "schema": "public",
      "table": "metadata"
    },
    {
      "type": "integer",
      "typeSchema": null,
      "notNull": false,
      "dimensions": 0,
      "default": null,
      "generated": null,
      "identity": null,
      "name": "content_length",
      "entityType": "columns",
      "schema": "public",
      "table": "metadata"
    },
    {
      "type": "integer",
      "typeSchema": null,
      "notNull": false,
      "dimensions": 0,
      "default": null,
      "generated": null,
      "identity": null,
      "name": "http_status_code",
      "entityType": "columns",
      "schema": "public",
      "table": "metadata"
    },
    {
      "type": "timestamp with time zone",
      "typeSchema": null,
      "notNull": false,
      "dimensions": 0,
      "default": "now()",
      "generated": null,
      "identity": null,
      "name": "created_at",
      "entityType": "columns",
      "schema": "public",
      "table": "metadata"
    },
    {
      "type": "integer",
      "typeSchema": null,
      "notNull": true,
      "dimensions": 0,
      "default": null,
      "generated": null,
      "identity": {
        "type": "always",
        "name": "search_index_id_seq",
        "increment": "1",
        "startWith": "1",
        "minValue": "1",
        "maxValue": "2147483647",
        "cache": 1,
        "cycle": false
      },
      "name": "id",
      "entityType": "columns",
      "schema": "public",
      "table": "search_index"
    },
    {
      "type": "varchar(255)",
      "typeSchema": null,
      "notNull": true,
      "dimensions": 0,
      "default": null,
      "generated": null,
      "identity": null,
      "name": "keyword",
      "entityType": "columns",
      "schema": "public",
      "table": "search_index"
    },
    {
      "type": "integer",
      "typeSchema": null,
      "notNull": true,
      "dimensions": 0,
      "default": null,
      "generated": null,
      "identity": null,
      "name": "url_id",
      "entityType": "columns",
      "schema": "public",
      "table": "search_index"
    },
    {
      "type": "integer",
      "typeSchema": null,
      "notNull": true,
      "dimensions": 0,
      "default": "1",
      "generated": null,
      "identity": null,
      "name": "frequency",
      "entityType": "columns",
      "schema": "public",
      "table": "search_index"
    },
    {
      "type": "timestamp with time zone",
      "typeSchema": null,
      "notNull": false,
      "dimensions": 0,
      "default": "now()",
      "generated": null,
      "identity": null,
      "name": "created_at",
      "entityType": "columns",
      "schema": "public",
      "table": "search_index"
    },
    {
      "type": "integer",
      "typeSchema": null,
      "notNull": true,
      "dimensions": 0,
      "default": null,
      "generated": null,
      "identity": {
        "type": "always",
        "name": "urls_id_seq",
        "increment": "1",
        "startWith": "1",
        "minValue": "1",
        "maxValue": "2147483647",
        "cache": 1,
        "cycle": false
      },
      "name": "id",
      "entityType": "columns",
      "schema": "public",
      "table": "urls"
    },
    {
      "type": "varchar(255)",
      "typeSchema": null,
      "notNull": true,
      "dimensions": 0,
      "default": null,
      "generated": null,
      "identity": null,
      "name": "url",
      "entityType": "columns",
      "schema": "public",
      "table": "urls"
    },
    {
      "type": "varchar(20)",
      "typeSchema": null,
      "notNull": true,
      "dimensions": 0,
      "default": "'pending'",
      "generated": null,
      "identity": null,
      "name": "status",
      "entityType": "columns",
      "schema": "public",
      "table": "urls"
    },
    {
      "type": "integer",
      "typeSchema": null,
      "notNull": true,
      "dimensions": 0,
      "default": "0",
      "generated": null,
      "identity": null,
      "name": "depth",
      "entityType": "columns",
      "schema": "public",
      "table": "urls"
    },
    {
      "type": "timestamp with time zone",
      "typeSchema": null,
      "notNull": false,
      "dimensions": 0,
      "default": null,
      "generated": null,
      "identity": null,
      "name": "last_crawled_at",
      "entityType": "columns",
      "schema": "public",
      "table": "urls"
    },
    {
      "type": "timestamp with time zone",
      "typeSchema": null,
      "notNull": false,
      "dimensions": 0,
      "default": "now()",
      "generated": null,
      "identity": null,
      "name": "created_at",
      "entityType": "columns",
      "schema": "public",
      "table": "urls"
    },
    {
      "type": "timestamp with time zone",
      "typeSchema": null,
      "notNull": false,
      "dimensions": 0,
      "default": "now()",
      "generated": null,
      "identity": null,
      "name": "updated_at",
      "entityType": "columns",
      "schema": "public",
      "table": "urls"
    },
    {
      "nameExplicit": false,
      "columns": [
        "url_id"
      ],
      "schemaTo": "public",
      "tableTo": "urls",
      "columnsTo": [
        "id"
      ],
      "onUpdate": "NO ACTION",
      "onDelete": "CASCADE",
      "name": "contents_url_id_urls_id_fkey",
      "entityType": "fks",
      "schema": "public",
      "table": "contents"
    },
    {
      "nameExplicit": false,
      "columns": [
        "source_url_id"
      ],
      "schemaTo": "public",
      "tableTo": "urls",
      "columnsTo": [
        "id"
      ],
      "onUpdate": "NO ACTION",
      "onDelete": "CASCADE",
      "name": "links_source_url_id_urls_id_fkey",
      "entityType": "fks",
      "schema": "public",
      "table": "links"
    },
    {
      "nameExplicit": false,
      "columns": [
        "url_id"
      ],
      "schemaTo": "public",
      "tableTo": "urls",
      "columnsTo": [
        "id"
      ],
      "onUpdate": "NO ACTION",
      "onDelete": "CASCADE",
      "name": "metadata_url_id_urls_id_fkey",
      "entityType": "fks",
      "schema": "public",
      "table": "metadata"
    },
    {
      "nameExplicit": false,
      "columns": [
        "url_id"
      ],
      "schemaTo": "public",
      "tableTo": "urls",
      "columnsTo": [
        "id"
      ],
      "onUpdate": "NO ACTION",
      "onDelete": "CASCADE",
      "name": "search_index_url_id_urls_id_fkey",
      "entityType": "fks",
      "schema": "public",
      "table": "search_index"
    },
    {
      "columns": [
        "id"
      ],
      "nameExplicit": false,
      "name": "contents_pkey",
      "schema": "public",
      "table": "contents",
      "entityType": "pks"
    },
    {
      "columns": [
        "id"
      ],
      "nameExplicit": false,
      "name": "links_pkey",
      "schema": "public",
      "table": "links",
      "entityType": "pks"
    },
    {
      "columns": [
        "id"
      ],
      "nameExplicit": false,
      "name": "metadata_pkey",
      "schema": "public",
      "table": "metadata",
      "entityType": "pks"
    },
    {
      "columns": [
        "id"
      ],
      "nameExplicit": false,
      "name": "search_index_pkey",
      "schema": "public",
      "table": "search_index",
      "entityType": "pks"
    },
    {
      "columns": [
        "id"
      ],
      "nameExplicit": false,
      "name": "urls_pkey",
      "schema": "public",
      "table": "urls",
      "entityType": "pks"
    },
    {
      "nameExplicit": false,
      "columns": [
        "url"
      ],
      "nullsNotDistinct": false,
      "name": "urls_url_key",
      "schema": "public",
      "table": "urls",
      "entityType": "uniques"
    }
  ],
  "renames": []
}